exec_helpers/__init__.py
exec_helpers/__init__.pyi
exec_helpers/_helpers.py
exec_helpers/_log_templates.py
exec_helpers/_ssh_base.py
exec_helpers/_ssh_helpers.py
exec_helpers/_subprocess_helpers.py
exec_helpers/_version.py
exec_helpers/api.py
exec_helpers/constants.py
exec_helpers/exceptions.py
exec_helpers/exec_result.py
exec_helpers/proc_enums.py
exec_helpers/py.typed
exec_helpers/ssh.py
exec_helpers/ssh_auth.py
exec_helpers/subprocess.py
exec_helpers/async_api/__init__.py
exec_helpers/async_api/__init__.pyi
exec_helpers/async_api/api.py
exec_helpers/async_api/exec_result.py
exec_helpers/async_api/subprocess.py
exec_helpers-8.1.2.dist-info/LICENSE
exec_helpers-8.1.2.dist-info/METADATA
exec_helpers-8.1.2.dist-info/WHEEL
exec_helpers-8.1.2.dist-info/top_level.txt
exec_helpers-8.1.2.dist-info/RECORD
