Metadata-Version: 2.1
Name: exec-helpers
Version: 8.1.2
Summary: Execution helpers for simplified usage of subprocess and ssh.
Home-page: https://github.com/python-useful-helpers/exec-helpers
Author-email: Alexey Stepanov <penguinolog@gmail.com>
Maintainer-email: Aleksei Stepanov <penguinolog@gmail.com>, Antonio Esposito <esposito.cloud@gmail.com>, Dennis Dmitriev <dis-xcom@gmail.com>
License: Apache-2.0
Project-URL: Documentation, https://exec-helpers.readthedocs.io/
Project-URL: Repository, https://github.com/python-useful-helpers/exec-helpers
Project-URL: Bug Tracker, https://github.com/python-useful-helpers/exec-helpers/issues
Keywords: subprocess,ssh
Classifier: Development Status :: 5 - Production/Stable
Classifier: Intended Audience :: Developers
Classifier: Topic :: Software Development :: Libraries :: Python Modules
Classifier: License :: OSI Approved :: Apache Software License
Classifier: Programming Language :: Python :: 3
Classifier: Programming Language :: Python :: 3 :: Only
Classifier: Programming Language :: Python :: 3.8
Classifier: Programming Language :: Python :: 3.9
Classifier: Programming Language :: Python :: 3.10
Classifier: Programming Language :: Python :: 3.11
Classifier: Programming Language :: Python :: 3.12
Classifier: Programming Language :: Python :: Implementation :: CPython
Classifier: Programming Language :: Python :: Implementation :: PyPy
Requires-Python: >=3.8.0
License-File: LICENSE
Requires-Dist: paramiko>=2.4
Requires-Dist: tenacity>=4.4.0
Requires-Dist: psutil>=5.0
Provides-Extra: all-formats
Requires-Dist: defusedxml; extra == "all-formats"
Requires-Dist: lxml>=4.6.2; extra == "all-formats"
Requires-Dist: PyYAML>=3.12; extra == "all-formats"
Provides-Extra: all_formats
Provides-Extra: lxml
Requires-Dist: lxml>=4.6.2; extra == "lxml"
Provides-Extra: xml
Requires-Dist: defusedxml; extra == "xml"
Provides-Extra: yaml
Requires-Dist: PyYAML>=3.12; extra == "yaml"
